bodhi/server/__init__.py
bodhi/server/auth/__init__.py
bodhi/server/auth/constants.py
bodhi/server/auth/fedora.py
bodhi/server/auth/oauth.py
bodhi/server/auth/oauth_015.py
bodhi/server/auth/oauth_1.py
bodhi/server/auth/utils.py
bodhi/server/auth/views.py
bodhi/server/bugs.py
bodhi/server/buildsys.py
bodhi/server/config.py
bodhi/server/consumers/__init__.py
bodhi/server/consumers/automatic_updates.py
bodhi/server/consumers/ci.py
bodhi/server/consumers/resultsdb.py
bodhi/server/consumers/signed.py
bodhi/server/consumers/util.py
bodhi/server/consumers/waiverdb.py
bodhi/server/email/templates/fedora_epel_errata_template.tpl
bodhi/server/email/templates/fedora_epel_legacy_errata_template.tpl
bodhi/server/email/templates/fedora_errata_template.tpl
bodhi/server/email/templates/fedora_modular_errata_template.tpl
bodhi/server/email/templates/maillist_template.tpl
bodhi/server/exceptions.py
bodhi/server/ffmarkdown.py
bodhi/server/locale/.placeholder
bodhi/server/logging.py
bodhi/server/mail.py
bodhi/server/metadata.py
bodhi/server/migrations/README.rst
bodhi/server/migrations/__init__.py
bodhi/server/migrations/env.py
bodhi/server/migrations/script.py.mako
bodhi/server/migrations/versions/16864f8ff395_remove_requirements_column_from_build_.py
bodhi/server/migrations/versions/190ba571c7d2_remove_the_batching_request_state.py
bodhi/server/migrations/versions/19e28e9851a2_index_comment_update_id.py
bodhi/server/migrations/versions/1c97477e38ee_convert_br_override_notes_to_unicodetext.py
bodhi/server/migrations/versions/2fc96aa44a74_drop_the_user_show_popup_column.py
bodhi/server/migrations/versions/325954bac9f7_link_testcases_to_builds.py
bodhi/server/migrations/versions/3a2e248d1757_add_the_unspecified_enum_to_updatetype.py
bodhi/server/migrations/versions/3b34650a0cf6_update_type_of_users_email_with_new_.py
bodhi/server/migrations/versions/499ac8bbe09a_remove_unused_update_sidetag_statuses.py
bodhi/server/migrations/versions/559acf7e2c16_make_comments_update_not_nullable.py
bodhi_server-25.11.3.dist-info/METADATA
bodhi_server-25.11.3.dist-info/WHEEL
bodhi_server-25.11.3.dist-info/entry_points.txt
bodhi_server-25.11.3.dist-info/licenses/COPYING
bodhi_server-25.11.3.dist-info/RECORD
