Metadata-Version: 2.4
Name: bodhi-server
Version: 25.11.3
Summary: Bodhi server
License: GPL-2.0-or-later
License-File: COPYING
Keywords: web,fedora,pyramid
Author: Fedora Infrastructure Team
Maintainer: Fedora Infrastructure Team
Maintainer-email: infrastructure@lists.fedoraproject.org
Requires-Python: >=3.9,<4
Classifier: Development Status :: 5 - Production/Stable
Classifier: Framework :: Pyramid
Classifier: Intended Audience :: Developers
Classifier: Intended Audience :: System Administrators
Classifier: License :: OSI Approved :: GNU General Public License v2 or later (GPLv2+)
Classifier: Operating System :: POSIX :: Linux
Classifier: Programming Language :: JavaScript
Classifier: Programming Language :: Python :: 3
Classifier: Programming Language :: Python :: 3.9
Classifier: Programming Language :: Python :: 3.10
Classifier: Programming Language :: Python :: 3.11
Classifier: Programming Language :: Python :: 3.12
Classifier: Programming Language :: Python :: 3.13
Classifier: Programming Language :: Python :: 3.14
Classifier: Topic :: Internet :: WWW/HTTP
Classifier: Topic :: Internet :: WWW/HTTP :: WSGI :: Application
Classifier: Topic :: System :: Software Distribution
Requires-Dist: Jinja2 (>=2.11.3)
Requires-Dist: Markdown (>=3.3.6)
Requires-Dist: SQLAlchemy (>=1.4,<2.1)
Requires-Dist: alembic (>=1.5.5)
Requires-Dist: arrow (>=0.17.0)
Requires-Dist: authlib (>=0.15.4)
Requires-Dist: backoff (>=1.10.0)
Requires-Dist: beautifulsoup4 (>=4.12.0,<5.0.0)
Requires-Dist: bleach (>=3.2.3)
Requires-Dist: bodhi-messages (>=8.1.1)
Requires-Dist: celery (>=5.2.1)
Requires-Dist: click (>=7.1.2)
Requires-Dist: colander (>=1.8.3)
Requires-Dist: cornice (>=5.0.3)
Requires-Dist: dogpile.cache (>=1.1.2)
Requires-Dist: fedora-messaging (>=3.0.0)
Requires-Dist: feedgen (>=0.9.0)
Requires-Dist: koji (>=1.27.1)
Requires-Dist: libcomps (>=0.1.20,<0.2.0)
Requires-Dist: munch (>=2.5.0)
Requires-Dist: packaging (>=21.3)
Requires-Dist: prometheus-client (>=0.13.1)
Requires-Dist: psycopg2 (>=2.8.6)
Requires-Dist: py3dns (>=3.2.1)
Requires-Dist: pyLibravatar (>=1.6)
Requires-Dist: pyasn1-modules (>=0.2.8)
Requires-Dist: pymediawiki (>=0.7,<0.8)
Requires-Dist: pyramid (>=2.0.0,<2.1.0)
Requires-Dist: pyramid-mako (>=1.1,<2.0)
Requires-Dist: python-bugzilla (>=3.2.0)
Requires-Dist: requests (>=2.25.1)
Requires-Dist: waitress (>=3.0.1,<4.0.0)
Requires-Dist: zstandard (>=0.21,<0.26.0)
Project-URL: Homepage, https://bodhi.fedoraproject.rog
Project-URL: Repository, https://github.com/fedora-infra/bodhi
